src/__init__.py
src/client.py
src/client/__init__.py
src/client/client_db.py
src/client/client_gui.py
src/client/connection.py
src/client/make_add.py
src/client/make_del.py
src/client/start_dialog.py
src/common/__init__.py
src/common/constants.py
src/common/decorators.py
src/common/descriptors.py
src/common/errors.py
src/common/metaclasses.py
src/common/utils.py
src/logs/__init__.py
src/logs/client_log_config.py
src/logs/server/__init__.py
src/logs/server/server_log_config.py
src/tests/__init__.py
sher_client_chat-0.0.1.dist-info/METADATA
sher_client_chat-0.0.1.dist-info/WHEEL
sher_client_chat-0.0.1.dist-info/top_level.txt
sher_client_chat-0.0.1.dist-info/RECORD
